dappier/__init__.py
dappier/api/__init__.py
dappier/api/async_client.py
dappier/api/client.py
dappier/dappier.py
dappier/types/__init__.py
dappier/types/ai_recommendations_request.py
dappier/types/ai_recommendations_response.py
dappier/types/constants.py
dappier/types/real_time_data_request.py
dappier/types/real_time_data_response.py
dappier/utils/__init__.py
dappier/utils/ai_recommendations_to_string.py
dappier-0.3.5.dist-info/LICENSE
dappier-0.3.5.dist-info/METADATA
dappier-0.3.5.dist-info/WHEEL
dappier-0.3.5.dist-info/RECORD
