Metadata-Version: 2.3
Name: dappier
Version: 0.3.5
Summary: The Dappier Python SDK provides an easy-to-use interface for interacting with the Dappier API.
Author: AI20labs
Author-email: dev@ai20labs.com
Requires-Python: >=3.9,<4.0
Classifier: Programming Language :: Python :: 3
Classifier: Programming Language :: Python :: 3.9
Classifier: Programming Language :: Python :: 3.10
Classifier: Programming Language :: Python :: 3.11
Classifier: Programming Language :: Python :: 3.12
Classifier: Programming Language :: Python :: 3.13
Requires-Dist: asyncio (>=3.4.3,<4.0.0)
Requires-Dist: httpx (>=0.23.0,<0.29.0)
Requires-Dist: pydantic (>=1.9,<3.0.0)
